ChatGPTonWhatsApp/__init__.py
ChatGPTonWhatsApp-0.0.3.dist-info/LICENSE.txt
ChatGPTonWhatsApp-0.0.3.dist-info/METADATA
ChatGPTonWhatsApp-0.0.3.dist-info/WHEEL
ChatGPTonWhatsApp-0.0.3.dist-info/top_level.txt
ChatGPTonWhatsApp-0.0.3.dist-info/RECORD
